{
  "id": "unit-56",
  "title": "C1 Entry Test — Advanced Comprehensive Test",
  "titleTr": "C1 Giris Testi — Ileri Kapsamli Test",
  "level": "C1",
  "module": 7,
  "description": "This is the C1 Entry Test — the most challenging assessment yet. Demonstrate mastery of inversion, cleft sentences, advanced modals, participle clauses, ellipsis, academic vocabulary, and advanced idioms. Live through Eyüp's complete executive week from crisis management to board reflection.",
  "descriptionTr": "Bu C1 Giris Testi — simdiye kadarki en zorlu degerlendirme. Ters cevirme, vurgulu cumleler, ileri kiplikler, ortac cümleleri, eksiltme, akademik kelime bilgisi ve ileri deyimlerde ustalik goster. Eyup'un kriz yonetiminden yonetim kurulu degerlendirmesine tam bir yonetici haftasini yasa.",

  "vocabulary": [
    { "word": "rarely", "pronunciation": "RER-li", "turkish": "nadiren / cok seyrek", "example": "Rarely have I seen such a well-structured proposal in my entire career.", "exampleTr": "Tum kariyerimde bu kadar iyi yapilandirilmis bir teklif nadiren gordum.", "extra": "When 'rarely' starts a sentence, use inversion: 'Rarely does the CEO attend morning standups.'", "extraTr": "'Rarely' cumle basinda oldugunda ters cevirme kullan: 'CEO nadiren sabah toplantilarina katilir.'" },
    { "word": "seldom", "pronunciation": "SEL-dım", "turkish": "nadiren / ender olarak", "example": "Seldom does a startup achieve profitability in its first year of operation.", "exampleTr": "Bir startup nadiren ilk faaliyet yilinda karliliga ulasir.", "extra": "Seldom is more formal than 'rarely' — use it in reports and presentations.", "extraTr": "'Seldom' 'rarely'den daha resmidir — raporlarda ve sunumlarda kullan." },
    { "word": "cleft sentence", "pronunciation": "KLEFT SEN-tıns", "turkish": "vurgulu cumle yapisi (It is... that/who)", "example": "It was the supply chain disruption that caused the quarterly loss, not the marketing budget.", "exampleTr": "Ceyreklik kayba neden olan pazarlama butcesi degil, tedarik zinciri aksamasiydi.", "extra": "Cleft sentences emphasize ONE specific element: 'It is innovation that drives our growth.'", "extraTr": "Vurgulu cumleler TEK bir unsuru vurgular: 'Buyumemizi sureukleyen yeniliktir.'" },
    { "word": "must have (done)", "pronunciation": "mast hev (dan)", "turkish": "yapmis olmali / kesin yapmistir (gecmis tahmin)", "example": "The server must have crashed during the night — all client data was inaccessible this morning.", "exampleTr": "Sunucu gece cokmul olmali — bu sabah tum musteri verilerine erisilemiyordu.", "extra": "Must have + PP = strong deduction about the past. 'They must have known about the risk.'", "extraTr": "Must have + PP = gecmis hakkinda guclu cikarim. 'Riski bilmis olmalilar.'" },
    { "word": "needn't have (done)", "pronunciation": "NID-ınt hev (dan)", "turkish": "yapmana gerek yoktu (ama yaptin)", "example": "We needn't have hired external consultants — our internal team had the expertise all along.", "exampleTr": "Dis danisman tutmamiza gerek yoktu — ic ekibimiz basindan beri uzmanliga sahipti.", "extra": "Needn't have ≠ didn't need to. 'Needn't have' = you DID it but it was unnecessary.", "extraTr": "Needn't have ≠ didn't need to. 'Needn't have' = YAPTIN ama gereksizdi." },
    { "word": "having completed", "pronunciation": "HE-ving kım-PLI-tid", "turkish": "tamamladiktan sonra (ortac cumle)", "example": "Having completed the due diligence, the board approved the acquisition unanimously.", "exampleTr": "Durum tespitini tamamladiktan sonra yonetim kurulu satin almayi oybirligiyle onayladi.", "extra": "Participle clauses replace 'after' clauses: 'Having reviewed the data, we made our decision.'", "extraTr": "Ortac cumleleri 'after' cumleciklerinin yerine gecer: 'Verileri inceledikten sonra kararimizi verdik.'" },
    { "word": "given that", "pronunciation": "GI-vın det", "turkish": "...dikkate alindiginda / ...goz onune alindiginda", "example": "Given that the market is volatile, we should diversify our investment portfolio.", "exampleTr": "Piyasanin oynak oldugu goz onune alindiginda, yatirim portfoyumuzu cesitlendirmeliyiz.", "extra": "Given that = considering that. Very common in formal analysis and executive summaries.", "extraTr": "Given that = dikkate alindiginda. Resmi analizlerde ve yonetici ozetlerinde cok yaygin." },
    { "word": "synthesize", "pronunciation": "SIN-tı-sayz", "turkish": "sentezlemek / birlestirmek / bir araya getirmek", "example": "A C1 speaker can synthesize information from multiple sources into a coherent argument.", "exampleTr": "Bir C1 konusmaci birden fazla kaynaktan bilgiyi tutarli bir argumana sentezleyebilir.", "extra": "The report synthesizes financial data, market trends, and competitor analysis.", "extraTr": "Rapor finansal verileri, piyasa trendlerini ve rakip analizini sentezliyor." },
    { "word": "extrapolate", "pronunciation": "iks-TRE-po-leyt", "turkish": "mevcut veriden sonuc cikarmak / tahmin etmek", "example": "Based on current trends, we can extrapolate that revenue will double within 18 months.", "exampleTr": "Mevcut trendlere dayanarak gelirin 18 ay icinde ikiye katlanacagini tahmin edebiliriz.", "extra": "Don't confuse extrapolate (predict from data) with speculate (guess without data).", "extraTr": "Extrapolate (veriden tahmin) ile speculate (verisiz tahmin) karistirma." },
    { "word": "articulate", "pronunciation": "ar-TI-kyu-lıt", "turkish": "acik ve etkili ifade etmek / duzgun konusan", "example": "She articulated the company's vision with such clarity that even skeptics were convinced.", "exampleTr": "Sirketin vizyonunu oyle netlikle ifade etti ki supheciler bile ikna oldu.", "extra": "As an adjective: 'He's very articulate' = he expresses himself clearly and effectively.", "extraTr": "Sifat olarak: 'He's very articulate' = kendini acik ve etkili ifade ediyor." },
    { "word": "eloquent", "pronunciation": "E-lo-kwınt", "turkish": "belagatli / etkileyici konusan / guc hitabet sahibi", "example": "His eloquent closing remarks at the conference earned a standing ovation.", "exampleTr": "Konferanstaki etkileyici kapanis konusmasi ayakta alkis aldi.", "extra": "Eloquent goes beyond articulate — it implies beauty and persuasion in speech.", "extraTr": "Eloquent articulate'in otesine gecer — konusmada guzellik ve ikna edicilik ima eder." },
    { "word": "discerning", "pronunciation": "di-SÖR-ning", "turkish": "secici / ayirt edici / ince zevkli", "example": "A discerning investor looks beyond the numbers to evaluate the team's integrity.", "exampleTr": "Secici bir yatirimci ekibin durustlugunu degerlendirmek icin rakamlarin otesine bakar.", "extra": "Discerning customers choose quality over price — they know the difference.", "extraTr": "Secici musteriler fiyat yerine kaliteyi secer — farki bilirler." },
    { "word": "astute", "pronunciation": "ıs-TYUT", "turkish": "zeki / kurnaz / keskin zekali", "example": "Her astute observation about the competitor's weakness changed our entire strategy.", "exampleTr": "Rakibin zayifligi hakkindaki keskin gozlemi tum stratejimizi degistirdi.", "extra": "Astute implies shrewdness — seeing things others miss. 'An astute business decision.'", "extraTr": "Astute kurnazlik ima eder — baskalArinin kacirdigi seyleri gormek. 'Keskin bir is karari.'" },
    { "word": "shrewd", "pronunciation": "SRUD", "turkish": "kurnaz / zeki / hesapci (olumlu anlamda)", "example": "The shrewd negotiator secured terms that saved the company $3 million annually.", "exampleTr": "Kurnaz muzakereci sirkete yillik 3 milyon dolar tasarruf saglayan sartlari elde etti.", "extra": "Shrewd = smart in a practical, street-smart way. Can be positive or slightly negative depending on context.", "extraTr": "Shrewd = pratik, sokak zekalisi anlaminda akilli. Baglama gore olumlu veya hafif olumsuz olabilir." },
    { "word": "prudent", "pronunciation": "PRU-dınt", "turkish": "tedbirli / ihtiyatli / basiretli", "example": "It would be prudent to secure additional funding before expanding into new markets.", "exampleTr": "Yeni pazarlara girmeden once ek finansman saglamak ihtiyatli olurdu.", "extra": "Prudent leadership means making careful decisions, not reckless ones.", "extraTr": "Ihtiyatli liderlik dikkatli kararlar almak demektir, pervasiz degil." },
    { "word": "meticulous", "pronunciation": "mı-TI-kyu-lıs", "turkish": "titiz / ozenli / kusursuz", "example": "Her meticulous attention to detail prevented a $2 million error in the financial report.", "exampleTr": "Detaylara titiz dikkati finansal rapordaki 2 milyon dolarlik bir hatayi onledi.", "extra": "Meticulous people don't miss anything — they check, double-check, and triple-check.", "extraTr": "Titiz insanlar hicbir seyi kacirmaz — kontrol eder, tekrar kontrol eder, ucuncu kez kontrol eder." },
    { "word": "tenacious", "pronunciation": "tı-NEY-sıs", "turkish": "azimli / inatci / vazgecmeyen", "example": "Her tenacious pursuit of the deal impressed even the most skeptical board members.", "exampleTr": "Anlasmay azimle kovalamasiı en supkeci yonetim kurulu uyelerini bile etkiledi.", "extra": "Tenacious is always positive — it means determined and never giving up.", "extraTr": "Tenacious her zaman olumludur — kararli ve asla pes etmeyen anlamina gelir." },
    { "word": "pragmatic", "pronunciation": "preg-ME-tik", "turkish": "pragmatik / pratik dusunceli / gercekci", "example": "We need a pragmatic approach — idealism won't solve our supply chain problems.", "exampleTr": "Pragmatik bir yaklasima ihtiyacimiz var — idealizm tedarik zinciri sorunlarimizi cozmeyecek.", "extra": "A pragmatic leader focuses on what WORKS, not what sounds good in theory.", "extraTr": "Pragmatik bir lider teoride iyi duyana degil, ISLEYEN seye odaklanir." },
    { "word": "strategic", "pronunciation": "strı-TI-cik", "turkish": "stratejik / planlI", "example": "The strategic decision to acquire the startup gave us access to AI technology we couldn't build in-house.", "exampleTr": "Startup'i satin almaya yonelik stratejik karar bize sirket ici yapamayacagimiz yapay zeka teknolojisine erisim sagladi.", "extra": "Strategic thinking means seeing the big picture and planning three moves ahead.", "extraTr": "Stratejik dusunme buyuk resmi gormek ve uc hamle ilerisini planlamak demektir." },
    { "word": "inversion", "pronunciation": "in-VÖR-jın", "turkish": "devrik cumle / ters cevirme", "example": "Not only did the team exceed targets, but they also set new industry records.", "exampleTr": "Ekip sadece hedefleri asmakla kalmadi, ayni zamanda yeni sektor rekorlari da kirdi.", "extra": "Inversion triggers: rarely, seldom, never, not only, hardly, no sooner, under no circumstances.", "extraTr": "Ters cevirme tetikleyicileri: rarely, seldom, never, not only, hardly, no sooner, under no circumstances." },
    { "word": "ellipsis", "pronunciation": "i-LIP-sis", "turkish": "eksiltme / sozcuk dusurme", "example": "A: 'Have you finished the report?' B: 'Not yet.' (= I have not finished it yet — ellipsis)", "exampleTr": "A: 'Raporu bitirdin mi?' B: 'Henuz degil.' (= Henuz bitirmedim — eksiltme)", "extra": "Ellipsis avoids repetition: 'She could have warned us, but she didn't.' (warn us is omitted)", "extraTr": "Eksiltme tekrardan kacinir: 'Bizi uyarabilirdi ama yapmadi.' (bizi uyarmak dusurulmustur)" },
    { "word": "discerning", "pronunciation": "di-SÖR-ning", "turkish": "secici / ayirt edici / titiz", "example": "Discerning readers will notice the subtle shift in the author's tone between chapters.", "exampleTr": "Secici okuyucular bolumler arasindaki yazarin tonundaki ince degisimi fark edecektir.", "extra": "A discerning palate, a discerning eye, a discerning mind — it works with many nouns.", "extraTr": "Secici bir damak, secici bir goz, secici bir zihin — bircok isimle calisir." },
    { "word": "astute", "pronunciation": "ıs-TYUT", "turkish": "keskin zekali / ferasetli", "example": "The CEO's astute reading of market signals allowed the company to pivot before the crash.", "exampleTr": "CEO'nun piyasa sinyallerini keskin okumasiı sirketin cokus oncesinde pivot yapmasina olanak sagladi.", "extra": "An astute observer, an astute analysis, an astute remark — implies insight and intelligence.", "extraTr": "Keskin bir gozlemci, keskin bir analiz, keskin bir yorum — kavrayis ve zeka ima eder." },
    { "word": "shrewd", "pronunciation": "SRUD", "turkish": "kurnaz / acikgoz / pratik zekali", "example": "It was a shrewd move to acquire the patent before competitors realized its value.", "exampleTr": "Rakipler degerini anlamadan once patenti satin almak kurnaz bir hamlEydi.", "extra": "Shrewd vs. cunning: shrewd is mostly positive (smart), cunning is mostly negative (manipulative).", "extraTr": "Shrewd vs. cunning: shrewd cogunlukla olumlu (akilli), cunning cogunlukla olumsuz (manipulatif)." },
    { "word": "prudent", "pronunciation": "PRU-dınt", "turkish": "ihtiyatli / basiretli / olculu", "example": "Given the current economic uncertainty, the most prudent course of action is to preserve cash reserves.", "exampleTr": "Mevcut ekonomik belirsizlik goz onune alindiginda, en ihtiyatli eylem yolu nakit rezervlerini korumaktir.", "extra": "Prudent ≠ cowardly. Prudent = wise caution based on analysis, not fear.", "extraTr": "Prudent ≠ korkak. Prudent = korkuya degil analize dayali akillica tedbir." },
    { "word": "meticulous", "pronunciation": "mı-TI-kyu-lıs", "turkish": "kusursuz / titiz / detayci", "example": "The meticulous audit revealed three previously undetected compliance gaps.", "exampleTr": "Titiz denetim daha once tespit edilmemis uc uyumluluk acigini ortaya cikardi.", "extra": "Meticulous planning, meticulous research, meticulous documentation — always implies thoroughness.", "extraTr": "Titiz planlama, titiz arastirma, titiz dokumantasyon — her zaman kapsalilik ima eder." },
    { "word": "tenacious", "pronunciation": "tı-NEY-sıs", "turkish": "inatci / kararli / birakmayi bilmeyen", "example": "Only the most tenacious negotiators survive multi-day acquisition talks.", "exampleTr": "Sadece en azimli muzakereciler gun suren satin alma gorusmelerini atlatir.", "extra": "Tenacious pursuit, tenacious defense, tenacious spirit — implies relentless determination.", "extraTr": "Azimli takip, azimli savunma, azimli ruh — amansiz kararlilik ima eder." },
    { "word": "pragmatic", "pronunciation": "preg-ME-tik", "turkish": "gercekci / islevsel / ayaklari yere basan", "example": "The most pragmatic solution isn't always the most elegant, but it gets results.", "exampleTr": "En pragmatik cozum her zaman en zarif olmayabilir ama sonuc verir.", "extra": "Pragmatic vs. idealistic: pragmatic = what works NOW, idealistic = what should work in theory.", "extraTr": "Pragmatik vs. idealist: pragmatik = SIMDI isleyen, idealist = teoride islemesi gereken." },
    { "word": "strategic", "pronunciation": "strı-TI-cik", "turkish": "stratejik / uzun vadeli plana dayali", "example": "Not only was the acquisition strategic, but it also eliminated our biggest competitor.", "exampleTr": "Satin alma sadece stratejik degildi, ayni zamanda en buyuk rakibimizi de eledi.", "extra": "Strategic patience, strategic alliance, strategic withdrawal — implies long-term thinking.", "extraTr": "Stratejik sabir, stratejik ittifak, stratejik geri cekilme — uzun vadeli dusunmeyi ima eder." }
  ],

  "grammar": {
    "title": "Full B2→C1 Review — Inversion, Cleft Sentences, Advanced Modals, Participle Clauses, Ellipsis & More",
    "titleTr": "Tam B2→C1 Tekrari — Ters Cevirme, Vurgulu Cumleler, Ileri Kiplikler, Ortac Cumleleri, Eksiltme ve Dahasi",
    "explanation": "This is the ultimate grammar review covering everything you need for C1 entry. You must master inversion (subject-verb flip after negative adverbs), cleft sentences (It is/was... that/who for emphasis), advanced modals (must have, needn't have, could have, should have for past deduction and regret), participle clauses (Having + PP, Given that), ellipsis (omitting words to avoid repetition), and integrating all of these with academic vocabulary and idiomatic expressions. A C1 speaker chains these structures naturally.",
    "explanationTr": "Bu, C1 giris icin ihtiyaciniz olan her seyi kapsayan nihai dilbilgisi tekraridir. Ters cevirme (olumsuz zarflardan sonra ozne-fiil degisimi), vurgulu cumleler (vurgu icin It is/was... that/who), ileri kiplikler (gecmis tahmin ve pismanlik icin must have, needn't have, could have, should have), ortac cumleleri (Having + PP, Given that), eksiltme (tekrardan kacinmak icin sozcuk dusurme) ve tum bunlari akademik kelime bilgisi ve deyimlerle butunlestirmeyi ustalasmalisiniz. Bir C1 konusmaci bu yapilari dogal olarak zincirler.",
    "table": [
      ["Inversion: Negative adverb + auxiliary + subject → 'Rarely have I seen such results.'", "Rarely does the board approve budgets without a full review.", "Not only did revenue increase, but profitability also improved by 15%.", "Triggers: rarely, seldom, never, hardly, no sooner, not only, under no circumstances, at no point."],
      ["Cleft Sentences: 'It is/was [focus] that/who [rest]' → emphasis on ONE element", "It was the team's meticulous preparation that secured the deal.", "What we need is a pragmatic approach, not more idealism.", "Use cleft sentences to correct, emphasize, or contrast: 'It wasn't price that lost us the client — it was delivery time.'"],
      ["Advanced Modals (past): must have (deduction), needn't have (unnecessary action), could have (missed opportunity)", "The server must have crashed overnight — all data was corrupted. (deduction)", "We needn't have postponed the launch — the weather cleared by noon. (unnecessary)", "Should have = regret/criticism. Must have = strong deduction. Needn't have = it happened but was pointless."],
      ["Participle Clauses: Having + PP (after doing), Given that (considering), Being + adj (because of being)", "Having completed the audit, the CFO presented findings to the board.", "Given that the market is volatile, a prudent approach would be to diversify.", "Participle clauses are more formal and concise than 'after/because' clauses — use in reports and presentations."],
      ["Ellipsis: Omitting repeated words → 'She could have warned us, but she didn't [warn us].'", "A: 'Will the board approve?' B: 'They should.' (= They should approve.)", "The Tokyo office exceeded targets; the London office didn't. (= didn't exceed targets)", "Ellipsis sounds natural in speech and writing. Repeating words sounds robotic at C1 level."],
      ["Academic Vocabulary: synthesize, extrapolate, articulate, eloquent, discerning, astute, shrewd, prudent", "The report synthesizes data from six quarterly reviews into a coherent narrative.", "An astute investor would extrapolate future trends from these early indicators.", "Academic vocabulary shows intellectual depth — use in reports, presentations, and executive communication."],
      ["Advanced Idiom Integration: Combine idioms with formal structures naturally", "It was the team's refusal to drink the Kool-Aid that saved us from a disastrous investment.", "Rarely has a startup weathered such a storm and emerged stronger.", "C1 mastery = formal grammar + strategic idioms + academic vocabulary in ONE coherent statement."]
    ],
    "tips": [
      { "en": "Inversion chain for maximum impact: 'Not only did we exceed targets, but rarely had the industry seen such rapid growth, and at no point did we compromise on quality.'", "tr": "Maksimum etki icin ters cevirme zinciri: 'Sadece hedefleri asmakla kalmadik, sektor nadiren bu kadar hizli buyume gormustu ve hicbir noktada kaliteden odun vermedik.'" },
      { "en": "Cleft sentence for correction: 'It wasn't the budget that failed us — it was the execution.' This structure is devastating in debates and presentations.", "tr": "Duzeltme icin vurgulu cumle: 'Bizi yarI yolda birakan butce degildi — uygulamaydi.' Bu yapi tartismalarda ve sunumlarda yikici etkiye sahiptir." },
      { "en": "Must have vs. should have: 'They must have known' (I'm almost certain they knew) vs. 'They should have known' (it was their responsibility to know, and they failed).", "tr": "Must have vs. should have: 'Bilmis olmalilar' (neredeyse kesin biliyorlardi) vs. 'Bilmeleri gerekirdi' (bilmek sorumlulklariydi ve basarisiz olduLar)." },
      { "en": "Needn't have trap: 'We needn't have rushed' = we DID rush, but it was unnecessary. 'We didn't need to rush' = we didn't rush because it wasn't necessary. Different meaning!", "tr": "Needn't have tuzagi: 'Acele etmemize gerek yoktu' = acele ETTIK ama gereksizdi. 'Acele etmeye ihtiyacimiz yoktu' = gerekli olmadigi icin acele etmedik. Farkli anlam!" },
      { "en": "Participle clause for elegance: Instead of 'After we completed the review, we submitted the report,' say 'Having completed the review, we submitted the report.' More concise, more C1.", "tr": "Zerafet icin ortac cumlesi: 'Incelemeyi tamamladiktan sonra raporu sunduk' yerine 'Incelemeyi tamamlayarak raporu sunduk.' Daha oz, daha C1." },
      { "en": "C1 power combo: Inversion + Idiom + Academic vocab = 'Rarely has such a meticulous analysis separated the wheat from the chaff so effectively.' Use in closing statements.", "tr": "C1 guc kombinasyonu: Ters cevirme + Deyim + Akademik kelime = 'Bu kadar titiz bir analiz nadiren iyiyi kotuden bu denli etkili ayirmistir.' Kapanis ifadelerinde kullan." }
    ]
  },

  "reading": {
    "text": "FROM B2 TO C1 — THE FINAL PUSH\n\nHaving completed the entire B2 curriculum, I find myself standing at the threshold of C1 — the level where English transforms from a skill you've learned into a language you live in. Rarely have I felt both so confident and so humbled at the same time.\n\nThe B2 journey gave me powerful tools. I mastered Past Perfect sequencing, Third Conditional analysis, Mixed Conditionals for connecting past decisions to present realities, and the causative passive that made my business English sound authoritative. I learned collocations that made my speech natural — 'drive growth,' 'mitigate risks,' 'secure funding.' I discovered idioms that gave my communication personality — from 'the elephant in the room' to 'pushing the envelope.' But C1 demands something fundamentally different.\n\nIt was not grammar rules that made B2 challenging — it was learning to THINK in English. And that is precisely what C1 amplifies. At C1, I must synthesize information from multiple sources, extrapolate conclusions from incomplete data, and articulate complex ideas with precision and nuance. The vocabulary shifts from functional to academic: 'discerning,' 'astute,' 'prudent,' 'meticulous.' These are not words you memorize — they are lenses through which you analyze the world.\n\nThe grammar structures at C1 are not new concepts but refined instruments. Inversion — 'Rarely does one encounter such complexity in entry-level assessments' — adds formality and emphasis. Cleft sentences — 'It was the consistent daily practice that made the difference, not natural talent' — allow me to control exactly what the listener focuses on. Advanced modals — 'We needn't have worried about the exam; the preparation was more than sufficient' — express subtle shades of meaning about past events.\n\nGiven that my ultimate goal is C1 mastery, I must acknowledge the challenges ahead. Participle clauses will replace my simpler 'after' and 'because' structures. Ellipsis will make my speech more natural by eliminating redundancy. Academic vocabulary will enable me to participate in intellectual discourse, not just business conversations. And advanced idioms will need to be deployed strategically — not scattered randomly, but placed precisely where they create maximum impact.\n\nNot only has this journey transformed my English, but it has also transformed my professional identity. At A1, I was a beginner who could barely order coffee. At B1, I was a competent professional who could participate in meetings. At B2, I became a confident communicator who could lead presentations and navigate complex negotiations. Now, at the threshold of C1, I aim to become an articulate, eloquent professional — someone whose English is not just correct but compelling.\n\nWhat I've learned about language learning itself is perhaps the most valuable insight: it is never the grammar book that teaches you a language — it is the courage to use it, make mistakes, and persist. Seldom have I undertaken a challenge this demanding, and never have I been more motivated to succeed. C1, I am ready. The final push begins now.",
    "textTr": "B2'DEN C1'E — SON HAMLE\n\nTum B2 mufredatini tamamladiktan sonra kendimi C1'in esiginde buluyorum — Ingilizce'nin ogrendigin bir beceriden yasadigin bir dile donustugu seviye. Ayni anda hem bu kadar ozguvenli hem bu kadar mahcup hissettigim nadiren olmustur.\n\nB2 yolculugu bana guclu araclar verdi. Past Perfect siralama, Ucuncu Kosul analizi, gecmis kararlari simdiki gercekliklere baglayan Karisik Kosullar ve is Ingilizce'mi otoriter yapan ettirgen edilgeni ustladim. Konusmami dogal yapan kolokasyonlar ogrendim — 'drive growth,' 'mitigate risks,' 'secure funding.' Iletisimime kisilik katan deyimler kesfettim — 'the elephant in the room'dan 'pushing the envelope'a. Ama C1 temelden farkli bir sey talep ediyor.\n\nB2'yi zorlu yapan dilbilgisi kurallari degildi — Ingilizce DUSUNMEYI ogrenmekti. Ve C1'in buyuttugu tam olarak bu. C1'de birden fazla kaynaktan bilgiyi sentezlemeli, eksik verilerden sonuclar cikarmali ve karmasik fikirleri hassasiyet ve nüansla ifade etmeliyim. Kelime bilgisi islevselden akademige kayiyor: 'discerning,' 'astute,' 'prudent,' 'meticulous.' Bunlar ezberleyecegin kelimeler degil — dunyayi analiz ettigin mercekler.\n\nC1'deki dilbilgisi yapilari yeni kavramlar degil, rafine edilmis araclar. Ters cevirme — 'Giris seviyesi degerlendirmelerde boyle bir karmasiklikla nadiren karsilasilir' — resmiyet ve vurgu ekler. Vurgulu cumleler — 'Farki yaratan dogal yetenek degil, tutarli gunluk pratikti' — dinleyicinin tam olarak neye odaklanacagini kontrol etmemi saglar. Ileri kiplikler — 'Sinav icin endiselenmemize gerek yoktu; hazirlik fazlasiyla yeterliydi' — gecmis olaylar hakkinda ince anlam tonlari ifade eder.\n\nNihai hedefimin C1 ustaligi oldugu goz onune alindiginda, ondeki zorluklari kabul etmeliyim. Ortac cumleleri daha basit 'after' ve 'because' yapilarimin yerini alacak. Eksiltme fazlaligi ortadan kaldirarak konusmami daha dogal yapacak. Akademik kelime bilgisi sadece is konusmalarinda degil entelektuel soylemlere katilmami saglayacak. Ve ileri deyimler stratejik olarak konuslandirilmali — rastgele dagitilmamali, en buyuk etkiyi yarattiklari yere tam olarak yerlestirilmeli.\n\nBu yolculuk sadece Ingilizce'mi degil, profesyonel kimligimi de donusturdu. A1'de zorlukla kahve siparis edebilen bir baslangic seviyesindeydim. B1'de toplantilara katilabilen yetkin bir profesyoneldim. B2'de sunumlara liderlik edebilen ve karmasik muzakerelerde yol alabilen ozguvenli bir iletisimci oldum. Simdi C1'in esiginde, acik ifade eden, etkileyici bir profesyonel olmayI hedefliyorum — Ingilizcesi sadece dogru degil ikna edici olan biri.\n\nDil ogrenimi hakkinda ogrendigim sey belki de en degerli icgoru: size bir dili ogreten asla dilbilgisi kitabi degil — onu kullanma, hata yapma ve israr etme cesaretidir. Bu kadar talepkar bir zorlugun altina nadiren girmisimdir ve basarmak icin hic bu kadar motivasyonlu olmamistim. C1, hazirim. Son hamle simdi basliyor.",
    "questions": [
      { "question": "According to Eyüp, what fundamentally changes between B2 and C1?", "questionTr": "Eyup'a gore B2 ve C1 arasinda temelden ne degisiyor?", "options": ["Grammar becomes harder", "English transforms from a learned skill to a lived language", "Vocabulary doubles", "Business English becomes unnecessary"], "correct": 1 },
      { "question": "Which grammar structure is demonstrated in: 'It was not grammar rules that made B2 challenging — it was learning to THINK in English'?", "questionTr": "'B2'yi zorlu yapan dilbilgisi kurallari degildi — Ingilizce DUSUNMEYI ogrenmekti' cumlesinde hangi yapi gosterilmis?", "options": ["Inversion", "Cleft sentence", "Participle clause", "Ellipsis"], "correct": 1 },
      { "question": "What does Eyüp say about the difference between B2 vocabulary and C1 vocabulary?", "questionTr": "Eyup B2 kelime bilgisi ile C1 kelime bilgisi arasindaki fark hakkinda ne soyluyor?", "options": ["C1 has fewer words", "B2 is functional, C1 is academic — words become analytical lenses", "They are the same", "C1 vocabulary is mostly idioms"], "correct": 1 },
      { "question": "Which inversion example appears in the text?", "questionTr": "Metinde hangi ters cevirme ornegi geciyor?", "options": ["Not only has this journey transformed my English, but it has also transformed my professional identity", "I feel confident and humbled", "C1 demands something different", "Grammar structures are refined instruments"], "correct": 0 },
      { "question": "What does Eyüp identify as the most valuable insight about language learning?", "questionTr": "Eyup dil ogrenme hakkinda en degerli icgoru olarak neyi tanimlIyor?", "options": ["Grammar books are essential", "Natural talent matters most", "It's the courage to use the language, make mistakes, and persist", "Watching movies is the best method"], "correct": 2 }
    ]
  },

  "exercises": {
    "fillBlanks": [
      { "sentence": "___ have I seen such a well-structured proposal in my career.", "answer": "Rarely", "hint": "Inversion — nadiren + auxiliary + subject" },
      { "sentence": "Not ___ did revenue increase, but profitability also improved.", "answer": "only", "hint": "Inversion — Not only did..." },
      { "sentence": "It ___ the team's preparation that secured the deal, not luck.", "answer": "was", "hint": "Cleft sentence — It was... that" },
      { "sentence": "The server ___ have crashed during the night — all data was corrupted.", "answer": "must", "hint": "Advanced modal — guclu gecmis tahmini" },
      { "sentence": "We ___ have hired consultants — our team had the expertise all along.", "answer": "needn't", "hint": "Advanced modal — gereksiz gecmis eylem" },
      { "sentence": "___ completed the audit, the CFO presented findings to the board.", "answer": "Having", "hint": "Participle clause — Having + PP" },
      { "sentence": "___ that the market is volatile, diversification is the prudent choice.", "answer": "Given", "hint": "Participle clause — Given that = dikkate alindiginda" },
      { "sentence": "She could have warned us, but she ___.", "answer": "didn't", "hint": "Ellipsis — sozcuk dusurme" },
      { "sentence": "The report ___ data from six quarterly reviews into a coherent narrative.", "answer": "synthesizes", "hint": "Academic vocab — sentezlemek" },
      { "sentence": "Based on current trends, we can ___ that revenue will double.", "answer": "extrapolate", "hint": "Academic vocab — mevcut veriden sonuc cikarmak" },
      { "sentence": "A ___ investor looks beyond the numbers to evaluate integrity.", "answer": "discerning", "hint": "Academic vocab — secici / ayirt edici" },
      { "sentence": "Her ___ attention to detail prevented a major financial error.", "answer": "meticulous", "hint": "Academic vocab — titiz / ozenli" },
      { "sentence": "___ does the board approve budgets without a full review.", "answer": "Seldom", "hint": "Inversion — nadiren / ender olarak" },
      { "sentence": "Under no circumstances ___ we compromise on data security.", "answer": "should", "hint": "Inversion — Under no circumstances + auxiliary + subject" },
      { "sentence": "It wasn't the budget that failed us — it ___ the execution.", "answer": "was", "hint": "Cleft sentence — vurgu degistirme" }
    ],
    "multipleChoice": [
      { "question": "'Rarely ___ the CEO attend morning standups.' Dogru tamamlama?", "options": ["do", "does", "did", "is"], "correct": 1 },
      { "question": "'Not only ___ we exceed targets, but we also set new records.' Dogru form?", "options": ["do", "did", "have", "were"], "correct": 1 },
      { "question": "'It ___ the consistent practice that made the difference.' Cleft sentence?", "options": ["is", "was", "has been", "were"], "correct": 1 },
      { "question": "'The server ___ have crashed overnight — all data is gone.' En uygun modal?", "options": ["could", "might", "must", "should"], "correct": 2 },
      { "question": "'We ___ have postponed the launch — the problem resolved itself.' Gereksiz eylem?", "options": ["shouldn't", "needn't", "mustn't", "couldn't"], "correct": 1 },
      { "question": "'___ completed the review, we submitted the final report.' Dogru baslangic?", "options": ["Have", "Having", "Had", "Being"], "correct": 1 },
      { "question": "'___ that the economy is unstable, caution is advised.' Dogru baglac?", "options": ["Given", "Giving", "Gave", "Give"], "correct": 0 },
      { "question": "'A: Will they approve? B: They ___.' Ellipsis — dogru tamamlama?", "options": ["will", "should", "might", "All are correct"], "correct": 3 },
      { "question": "'She articulated the vision with clarity.' 'Articulate' burada ne anlama gelir?", "options": ["Eklemli", "Acik ve etkili ifade etmek", "Seslendirmek", "Yazmak"], "correct": 1 },
      { "question": "Hangisi 'mevcut veriden sonuc cikarmak' anlamina gelir?", "options": ["synthesize", "extrapolate", "articulate", "discern"], "correct": 1 },
      { "question": "'Under no circumstances ___ we reveal this information.' Dogru form?", "options": ["do", "should", "will", "All are correct"], "correct": 3 },
      { "question": "'Needn't have done' ne anlama gelir?", "options": ["Yapmana gerek yoktu (ve yapmadin)", "Yapmana gerek yoktu (ama yaptin)", "Yapmaliydin (ama yapmadin)", "Yapamadin"], "correct": 1 },
      { "question": "'Seldom ___ a startup achieve profitability in year one.' Dogru tamamlama?", "options": ["do", "does", "did", "has"], "correct": 1 },
      { "question": "Cleft sentence hangisidir?", "options": ["The team worked hard.", "It was the team that worked hard.", "Hard work was done by the team.", "Working hard, the team succeeded."], "correct": 1 },
      { "question": "'An ___ negotiator sees opportunities others miss.' En uygun sifat?", "options": ["eloquent", "meticulous", "astute", "prudent"], "correct": 2 }
    ],
    "matching": [
      { "left": "rarely / seldom", "right": "ters cevirme tetikleyici — nadiren" },
      { "left": "It was... that/who", "right": "vurgulu cumle yapisi (cleft)" },
      { "left": "must have + PP", "right": "gecmis hakkinda guclu tahmin" },
      { "left": "needn't have + PP", "right": "gereksiz gecmis eylem" },
      { "left": "Having + PP", "right": "ortac cumlesi (tamamladiktan sonra)" },
      { "left": "Given that", "right": "goz onune alindiginda" },
      { "left": "ellipsis", "right": "tekrardan kacinmak icin sozcuk dusurme" },
      { "left": "synthesize", "right": "sentezlemek / birlestirmek" },
      { "left": "extrapolate", "right": "mevcut veriden sonuc cikarmak" },
      { "left": "articulate (verb)", "right": "acik ve etkili ifade etmek" },
      { "left": "eloquent", "right": "etkileyici konusan / belagatli" },
      { "left": "discerning", "right": "secici / ayirt edici" },
      { "left": "astute", "right": "keskin zekali / ferasetli" },
      { "left": "shrewd", "right": "kurnaz / pratik zekali" },
      { "left": "prudent", "right": "ihtiyatli / basiretli" },
      { "left": "meticulous", "right": "titiz / ozenli" },
      { "left": "tenacious", "right": "azimli / vazgecmeyen" },
      { "left": "pragmatic", "right": "gercekci / pratik dusunceli" },
      { "left": "strategic", "right": "stratejik / uzun vadeli" },
      { "left": "inversion", "right": "devrik cumle / ters cevirme" },
      { "left": "Not only... but also", "right": "sadece... degil ayni zamanda" },
      { "left": "Under no circumstances", "right": "hicbir kosulda" },
      { "left": "should have + PP", "right": "gecmis pismanlik / elestiri" },
      { "left": "could have + PP", "right": "kacirilan firsat" },
      { "left": "cleft sentence", "right": "vurgulu cumle yapisi" },
      { "left": "participle clause", "right": "ortac cumlesi" },
      { "left": "No sooner... than", "right": "daha... yapar yapmaz" },
      { "left": "Hardly... when", "right": "neredeyse hic... -diginda" },
      { "left": "At no point", "right": "hicbir noktada" },
      { "left": "What we need is...", "right": "ihtiyacimiz olan... (cleft varyant)" }
    ],
    "sentenceOrder": [
      { "words": ["Rarely", "have", "I", "seen", "such", "a", "well-structured", "proposal"], "correct": "Rarely have I seen such a well-structured proposal" },
      { "words": ["Not", "only", "did", "revenue", "increase", "but", "profitability", "also", "improved"], "correct": "Not only did revenue increase but profitability also improved" },
      { "words": ["It", "was", "the", "team's", "preparation", "that", "secured", "the", "deal"], "correct": "It was the team's preparation that secured the deal" },
      { "words": ["The", "server", "must", "have", "crashed", "during", "the", "night"], "correct": "The server must have crashed during the night" },
      { "words": ["We", "needn't", "have", "hired", "external", "consultants"], "correct": "We needn't have hired external consultants" },
      { "words": ["Having", "completed", "the", "audit", "the", "CFO", "presented", "findings"], "correct": "Having completed the audit the CFO presented findings" },
      { "words": ["Given", "that", "the", "market", "is", "volatile", "diversification", "is", "prudent"], "correct": "Given that the market is volatile diversification is prudent" },
      { "words": ["Under", "no", "circumstances", "should", "we", "compromise", "on", "quality"], "correct": "Under no circumstances should we compromise on quality" },
      { "words": ["Seldom", "does", "a", "startup", "achieve", "profitability", "in", "year", "one"], "correct": "Seldom does a startup achieve profitability in year one" },
      { "words": ["It", "wasn't", "the", "budget", "that", "failed", "us", "it", "was", "execution"], "correct": "It wasn't the budget that failed us it was execution" }
    ],
    "translation": [
      { "turkish": "Kariyerimde bu kadar iyi yapilandirilmis bir teklif nadiren gordum.", "english": "Rarely have I seen such a well-structured proposal in my career.", "acceptAlso": ["Seldom have I seen such a well-structured proposal in my career."] },
      { "turkish": "Sadece gelir artmakla kalmadi, karlilik da iyilesti.", "english": "Not only did revenue increase, but profitability also improved.", "acceptAlso": ["Not only did revenue grow, but profitability also improved."] },
      { "turkish": "Anlasmayi saglayan ekibin hazirligiydi, sans degil.", "english": "It was the team's preparation that secured the deal, not luck.", "acceptAlso": ["It was the team's preparation, not luck, that secured the deal."] },
      { "turkish": "Sunucu gece cokmul olmali — tum veriler bozulmus.", "english": "The server must have crashed during the night — all data was corrupted.", "acceptAlso": ["The server must have crashed overnight — all data is corrupted."] },
      { "turkish": "Dis danisman tutmamiza gerek yoktu — ic ekibimiz uzmanliga sahipti.", "english": "We needn't have hired external consultants — our internal team had the expertise.", "acceptAlso": ["We needn't have hired outside consultants — our team had the expertise all along."] },
      { "turkish": "Denetimi tamamladiktan sonra CFO bulgulari kurula sundu.", "english": "Having completed the audit, the CFO presented findings to the board.", "acceptAlso": ["Having completed the audit, the CFO presented the findings."] },
      { "turkish": "Piyasanin oynak oldugu goz onune alindiginda cesitlendirme ihtiyatli bir secimdir.", "english": "Given that the market is volatile, diversification is a prudent choice.", "acceptAlso": ["Given that the market is volatile, diversification is the prudent choice."] },
      { "turkish": "Hicbir kosulda veri guvenliginden odun vermemeliyiz.", "english": "Under no circumstances should we compromise on data security.", "acceptAlso": ["Under no circumstances must we compromise on data security."] },
      { "turkish": "Bir startup nadiren ilk yilinda karliliga ulasir.", "english": "Seldom does a startup achieve profitability in its first year.", "acceptAlso": ["Rarely does a startup achieve profitability in year one."] },
      { "turkish": "Bizi yarI yolda birakan butce degildi — uygulamaydi.", "english": "It wasn't the budget that failed us — it was the execution.", "acceptAlso": ["It was not the budget that failed us — it was execution."] }
    ]
  },

  "dialog": {
    "title": "Eyüp's Executive Week — From Crisis to Confidence",
    "titleTr": "Eyup'un Yonetici Haftasi — Krizden Ozguvene",
    "context": "Eyup'un C1 seviyesindeki tam bir yonetici haftasi: Pazartesi kriz yonetimi (sunucu cokusu), Sali konferans sunumu, Carsamba muzakere, Persembe yonetim kurulu, Cuma yansitma. Her gun farkli C1 yapilarini kullanIyor: inversion, cleft sentences, advanced modals, participle clauses, ellipsis.",
    "lines": [
      { "speaker": "A", "speakerName": "CTO Sarah", "text": "Eyüp, we have a critical situation. The main server cluster crashed at 3 AM. All client-facing services are down. The engineering team has been working since dawn, but we're still at 40% capacity. The board wants an update in two hours.", "textTr": "Eyup, kritik bir durumumuz var. Ana sunucu kumesi sabah 3'te coktu. Tum musteriye yonelik hizmetler kapali. Muhendislik ekibi safaktan beri calisiyor ama hala %40 kapasitedeyiz. Yonetim kurulu iki saat icinde guncelleme istiyor.", "gender": "female" },
      { "speaker": "B", "speakerName": "Eyüp", "text": "Thank you, Sarah. First — the backup systems must have failed to activate automatically. That shouldn't have happened. Having reviewed our disaster recovery protocol last quarter, I know we have redundancy in place. What went wrong with the failover?", "textTr": "Tesekkurler Sarah. Oncelikle — yedek sistemler otomatik olarak devreye girmemis olmali. Bu olmamaliydi. Gecen ceyrek felaket kurtarma protokolumuzu inceledigimden, yerimizde yedeklilik oldugunu biliyorum. Yuk devretmede ne yanlis gitti?" },
      { "speaker": "A", "speakerName": "CTO Sarah", "text": "The failover triggered, but the secondary cluster was running on outdated firmware. We needn't have delayed the firmware update last month — that decision has cost us dearly.", "textTr": "Yuk devretme tetiklendi ama ikincil kume guncel olmayan yazilimla calisiyordu. Gecen ay yazilim guncellemesini ertelememize gerek yoktu — o karar bize pahali mal oldu.", "gender": "female" },
      { "speaker": "B", "speakerName": "Eyüp", "text": "Understood. Under no circumstances should we allow this to happen again. Here's what I need: a full incident report by noon, client communication drafted by 10 AM, and a remediation plan by end of day. It isn't the crash itself that concerns me — it's the fact that our failover wasn't bulletproof.", "textTr": "Anlasildi. Hicbir kosulda bunun tekrar olmasina izin vermemeliyiz. Ihtiyacim olan: oglen'e kadar tam olay raporu, sabah 10'a kadar musteri iletisimi taslagi ve gun sonuna kadar duzeltme plani. Beni endIselendiren cokusun kendisi degil — yuk devretmenin kusursuz olmamasidir." },
      { "speaker": "A", "speakerName": "CTO Sarah", "text": "Agreed. Should I also loop in our cloud provider? They could have flagged the firmware incompatibility if we had asked them to audit the system.", "textTr": "Katiliyorum. Bulut saglayicimizi da dahil edeyim mi? Sistemi denetlemelerini isteseydik yazilim uyumsuzlugunu isaret edebilirlerdi.", "gender": "female" },
      { "speaker": "B", "speakerName": "Eyüp", "text": "Absolutely. And Sarah — not only do we need to fix the immediate issue, but we also need to ensure this never falls through the cracks again. Let's implement automated firmware checks across all clusters. Given that our reputation depends on uptime, this is non-negotiable.", "textTr": "Kesinlikle. Ve Sarah — sadece acil sorunu cozmemiz gerekmekle kalmiyor, ayni zamanda bunun bir daha asla gozden kacmamasini saglamamiz gerekiyor. Tum kumelerde otomatik yazilim kontrollerini uygulayalim. Itibarimizin calisma suresine bagli oldugu goz onune alindiginda, bu pazarlik konusu degildir." },
      { "speaker": "A", "speakerName": "Conference Moderator", "text": "Welcome to the Global Tech Summit. Our next keynote speaker is Eyüp from NovaTech Solutions, presenting on 'Strategic Resilience in the Age of Disruption.' Please welcome Eyüp.", "textTr": "Kuresel Teknoloji Zirvesi'ne hosgeldiniz. Bir sonraki ana konusmacimiz NovaTech Solutions'tan Eyup, 'Aksama Caginda Stratejik Dayaniklilik' sunumuyla. Lutfen Eyup'u karsilayalim.", "gender": "female" },
      { "speaker": "B", "speakerName": "Eyüp", "text": "Thank you. Rarely does a conference title capture reality as accurately as this one. We are indeed living in an age of disruption. But here's what I want to challenge today: disruption is not the enemy — complacency is. It was not the market crash of 2024 that destroyed companies — it was their refusal to adapt.", "textTr": "Tesekkurler. Bir konferans basligi gercekligi bu kadar dogrusu yakalamin nadiren gerceklesir. Gercekten bir aksama caginda yasiyoruz. Ama bugUN meydan okumak istedigim sey su: aksama dusman degil — kayitsizlik dusman. 2024 piyasa cokusunun sirketleri yok etmesi degil — onlarin uyum saglamayi reddetmesi yok etti." },
      { "speaker": "B", "speakerName": "Eyüp", "text": "At NovaTech, we faced our own disruption just yesterday — a critical server failure. Having managed the crisis in real-time, I can tell you this: it is not the systems that save you — it is the people and processes behind them. Our team synthesized data from multiple monitoring tools, extrapolated the root cause within two hours, and had full service restored by noon.", "textTr": "NovaTech'te daha dun kendi aksamawizi yasadik — kritik bir sunucu arizasi. Krizi gercek zamanli yonettikten sonra size sunu soyleyebilirim: sizi kurtaran sistemler degil — arkalarindaki insanlar ve surecler. Ekibimiz birden fazla izleme aracindan verileri sentezledi, iki saat icinde temel nedeni cikardi ve ogLen'e kadar tam hizmeti geri yukledI." },
      { "speaker": "B", "speakerName": "Eyüp", "text": "Seldom has a crisis taught us more. We learned that no sooner had we restored one service than another dependency surfaced. We learned that our disaster recovery, while robust, needn't have been so complex — simplicity would have accelerated our response. And we learned that a meticulous post-mortem is worth more than any prevention plan written in theory.", "textTr": "Bir kriz bize nadiren daha fazlasini ogretmistir. Bir hizmeti geri yukler yuklemez baska bir bagimliligin ortaya ciktigini ogrendik. Felaket kurtarmamizin saglamken bu kadar karmasik olmasina gerek olmadigini ogrendik — basitlik yanitmizi hizlandirirdi. Ve titiz bir olay sonrasi analIzin teoride yazilan herhangi bir onleme planinan daha degerli oldugunu ogrendik." },
      { "speaker": "A", "speakerName": "Negotiation Partner (Mr. Tanaka)", "text": "Eyüp-san, thank you for meeting today. We've reviewed your partnership proposal. Frankly, while the technology is impressive, the terms are... ambitious. We would need significant adjustments before proceeding.", "textTr": "Eyup-san, bugun bulustugunuz icin tesekkurler. Ortaklik teklifinizi inceledik. Acikca soylersek, teknoloji etkileyici olsa da sartlar... iddiali. Devam etmeden once onemli ayarlamalara ihtiyacimiz olurdu.", "gender": "male" },
      { "speaker": "B", "speakerName": "Eyüp", "text": "Thank you, Mr. Tanaka. I appreciate your candor. Given that both companies stand to benefit substantially, I'm confident we can find common ground. What specific terms concern you most?", "textTr": "Tesekkurler Bay Tanaka. AciksoZlulugunuzu takdir ediyorum. Her iki sirketin de onemli olcude fayda saglayacagi goz onune alindiginda, ortak bir zemin bulabilecegimize eminim. Hangi spesifik sartlar sizi en cok endiselendiriyor?" },
      { "speaker": "A", "speakerName": "Mr. Tanaka", "text": "The revenue share model. You proposed 60-40 in NovaTech's favor. Had we been a smaller company without existing distribution networks, that might have been acceptable. But we bring significant infrastructure to the table.", "textTr": "Gelir paylasim modeli. NovaTech lehine 60-40 onerilmistiniz. Mevcut dagitim aglari olmayan daha kucuk bir sirket olsaydik, bu kabul edilebilir olabilirdi. Ama masaya onemli altyapi getiriyoruz.", "gender": "male" },
      { "speaker": "B", "speakerName": "Eyüp", "text": "You make a fair point. It was our initial position, not our final one. What I'd propose is a tiered model: 55-45 for the first year, moving to 50-50 once we achieve mutual revenue targets. That way, neither company bears disproportionate risk. Not only does this align incentives, but it also demonstrates that we have skin in the game equally.", "textTr": "Adil bir nokta. Bu baslangic pozisyonumuzdu, nihai degil. Onerdigim kademeli bir model: ilk yil 55-45, karsilikli gelir hedeflerine ulasinca 50-50'ye gecis. Boylece hicbir sirket orantisiz risk tasimiyor. Bu sadece tesvikleri hizalamakla kalmaz, ayni zamanda oyunda esit paylariMiz oldugunu da gosterir." },
      { "speaker": "A", "speakerName": "Mr. Tanaka", "text": "That's a shrewd proposal, Eyüp-san. My board could work with a tiered structure. But I must ask — what happens if targets aren't met? We needn't have entered the APAC market last year to know that projections don't always materialize.", "textTr": "Bu kurnaz bir teklif Eyup-san. Kurulum kademeli bir yapiyla calisabilir. Ama sormam gerekiyor — hedeflere ulasilamazsa ne olur? Projeksiyonlarin her zaman gerceklesmediklerini bilmek icin gecen yil APAC pazarina girmemize gerek yoktu.", "gender": "male" },
      { "speaker": "B", "speakerName": "Eyüp", "text": "An astute question. We'd include a mutual exit clause activated after 18 months if neither party achieves 70% of projected targets. Having learned from previous partnerships that ambiguity creates conflict, we would articulate every metric clearly in the agreement. Transparency is non-negotiable for us.", "textTr": "Keskin bir soru. Her iki taraf da hedeflenen hedeflerin %70'ine ulasmazsa 18 ay sonra devreye giren karsilikli cikis maddesi ekleriz. Onceki ortakliklardan belirsizligin catisma yarattigini ogrenmis olarak, anlasmada her metrigi acikca ifade ederdik. Seffaflik bizim icin pazarlik konusu degildir." },
      { "speaker": "A", "speakerName": "Board Chair (Mr. Henderson)", "text": "Good morning, board. This has been an extraordinary week for NovaTech. Eyüp, please give us the comprehensive weekly review.", "textTr": "Gunaydin kurul. NovaTech icin olaganustu bir hafta oldu. Eyup, lutfen bize kapsamli haftalik degerlendirmeyi ver.", "gender": "male" },
      { "speaker": "B", "speakerName": "Eyüp", "text": "Thank you, Mr. Henderson. Having navigated a server crisis on Monday, delivered a keynote on Tuesday, and closed a strategic partnership on Wednesday, I can report that this was the most demanding yet rewarding week in my tenure. Let me synthesize the key outcomes.", "textTr": "Tesekkurler Bay Henderson. Pazartesi sunucu krizini yonettikten, Sali ana konusma yaptiKtan ve Carsamba stratejik ortakligi kapattiktan sonra raporlayabilirim ki bu gorev suremimdeki en talepkar ama en odullendirici haftaydi. Temel sonuclari sentezleyeyim." },
      { "speaker": "B", "speakerName": "Eyüp", "text": "First: the server crisis. It was the firmware oversight, not the infrastructure itself, that caused the failure. We needn't have delayed the update — that lesson has been internalized. The remediation plan is already implemented, and automated firmware monitoring is now active across all clusters.", "textTr": "Birincisi: sunucu krizi. Arizaya neden olan altyapinin kendisi degil, yazilim gozdenkacirilmasiydi. Guncellemeyi ertelememize gerek yoktu — bu ders icerilestirrildi. Duzeltme plani zaten uygulandı ve otomatik yazilim izleme artik tum kumelerde aktif." },
      { "speaker": "B", "speakerName": "Eyüp", "text": "Second: the conference keynote generated 47 qualified leads and three partnership inquiries. Rarely has a single presentation yielded such immediate business value. The key message — that resilience comes from people, not systems — resonated deeply with the C-suite audience.", "textTr": "Ikincisi: konferans ana konusmasi 47 nitelikli potansiyel musteri ve uc ortaklik sorusu uretti. Tek bir sunum nadiren bu kadar aninda is degeri olusturmustur. Temel mesaj — dayanIkliligin sistemlerden degil insanlardan geldigi — ust yonetim dinleyicileriyle derinden yanki buldu." },
      { "speaker": "B", "speakerName": "Eyüp", "text": "Third: the Tanaka partnership. Given that their distribution network covers 14 APAC markets, this alliance is transformative. We agreed on a tiered revenue model — 55-45 moving to 50-50 — with clear exit clauses. Not only does this give us market access, but it also validates our technology in the world's fastest-growing region.", "textTr": "Ucuncusu: Tanaka ortakligi. Dagitim aglarinin 14 APAC pazarini kapsamasi goz onune alindiginda, bu ittifak donusturucu. Kademeli gelir modelinde anlastik — 55-45'ten 50-50'ye gecis — acik cikis maddeleriyle. Bu bize sadece pazar erisimi saglamakla kalmiyor, ayni zamanda teknolojimizi dunyanin en hizli buyuyen bolgesinde dogruluyor." },
      { "speaker": "A", "speakerName": "Board Member (Ms. Chen)", "text": "Impressive week, Eyüp. But I need to ask a prudent question — are we stretching too thin? Three major initiatives in one week is ambitious. Could we have been more strategic about the timing?", "textTr": "Etkileyici hafta Eyup. Ama ihtiyatli bir soru sormam gerekiyor — kendimizi fazla mi zorluyoruz? Bir haftada uc buyuk girisim iddiali. Zamanlama konusunda daha stratejik olabilir miydik?", "gender": "female" },
      { "speaker": "B", "speakerName": "Eyüp", "text": "An astute observation, Ms. Chen. In hindsight, could we have spaced these out? Perhaps. But the crisis wasn't planned, the conference date was fixed, and the Tanaka meeting window was narrow. What matters is that at no point did quality suffer. The team was tenacious, the execution was meticulous, and the outcomes speak for themselves.", "textTr": "Keskin bir gozlem Bayan Chen. Geriye bakIldiginda bunlari daha araliKli yapabilir miydik? Belki. Ama kriz planli degildi, konferans tarihi sabitlenMisti ve Tanaka toplanti penceresi dardiI. Onemli olan hicbir noktada kalitenin zarar gormedigi. Ekip azimli, uygulama titiz ve sonuclar kendini anlatiyor." },
      { "speaker": "B", "speakerName": "Eyüp (Friday reflection)", "text": "What a week. Rarely have five days packed so much learning, pressure, and growth into one stretch. Monday's crisis taught me that it is preparation, not luck, that determines outcomes. Tuesday's keynote reminded me that seldom does an audience connect with data alone — they connect with stories, with vulnerability, with honesty. Wednesday's negotiation proved that a pragmatic, transparent approach builds trust faster than any shrewd tactic. Thursday's board meeting showed that having synthesized a complex week into clear outcomes earns respect and credibility. And today, Friday — I reflect. Having started this journey at A1, barely able to order coffee, I now stand at the threshold of C1 — articulating complex ideas, navigating high-stakes situations, and leading in English. Not only has the language changed — I have changed. The tenacious student who refused to give up is now a strategic professional who extrapolates trends, synthesizes data, and communicates with eloquence. C1 is not the destination. It's the beginning of true fluency. And I am ready.", "textTr": "Ne haftaymis. Bes gunun bir zaman dilimine bu kadar cok ogrenme, baski ve buyume sigdirmasi nadiren olmustur. Pazartesinin krizi bana sonuclari belirleyenin sans degil hazirlik oldugunu ogretti. Salinin ana konusmasi bir dinleyicinin nadiren sadece verilerle baglandigini — hikayelerle, kirilganlikla, durustlukle baglandigini hatirlatti. Carsambarnin muzakeresi pragmatik, seffaf bir yakla siminin guvenI herhangi bir kurnaz taktikten daha hizli insa ettigini kanIkladi. Persembenin yonetim kurulu toplantisi karmasik bir haftayi net sonuclara sentezlemis olmanin saygi ve guvenilirlik kazandigini gosterdi. Ve bugun, Cuma — dusunuyorum. Bu yolculuga A1'de baslayarak, zorlukla kahve siparis edebilirken, simdi C1'in esiginde duruyorum — karmasik fikirleri ifade ederek, yuksek riskli durumlarda yol alarak ve Ingilizce liderlik ederek. Sadece dil degismedi — ben degistim. Pes etmeyi reddeden azimli ogrenci simdi trendleri tahmin eden, verileri sentezleyen ve etkili iletisim kuran stratejik bir profesyonel. C1 varil noktasi degil. Gercek akiciligin baslangici. Ve ben hazirim." }
    ],
    "questions": [
      { "question": "What caused the server crisis on Monday?", "questionTr": "Pazartesi sunucu krizine ne sebep oldu?", "options": ["Hardware failure", "Cyber attack", "Outdated firmware on the secondary cluster", "Power outage"], "correct": 2 },
      { "question": "Which C1 grammar structure is used in: 'It was not the market crash that destroyed companies — it was their refusal to adapt'?", "questionTr": "'Sirketleri yok eden piyasa cokusu degildi — uyum saglamayi reddetmeleriydi' cumlesinde hangi C1 yapisi kullanilmis?", "options": ["Inversion", "Cleft sentence", "Participle clause", "Ellipsis"], "correct": 1 },
      { "question": "What revenue share model did Eyüp propose to Mr. Tanaka?", "questionTr": "Eyup Bay Tanaka'ya hangi gelir paylasim modelini onerdi?", "options": ["60-40 fixed", "50-50 from day one", "55-45 moving to 50-50 based on targets", "70-30 in Tanaka's favor"], "correct": 2 },
      { "question": "What did Eyüp identify as the key lesson from Tuesday's keynote?", "questionTr": "Eyup Sali ana konusmasIndan cikardigi temel dersi ne olarak belirlemisti?", "options": ["Data is everything", "Audiences connect with stories and honesty, not just data", "Presentations should be short", "Technology sells itself"], "correct": 1 },
      { "question": "In his Friday reflection, which inversion structure does Eyüp use?", "questionTr": "Cuma dusuncesinde Eyup hangi ters cevirme yapisini kullaniyor?", "options": ["Under no circumstances did he fail", "Rarely have five days packed so much learning", "Never would he forget this", "Hardly had he started when it ended"], "correct": 1 }
    ]
  },

  "resources": [
    { "title": "Cambridge C1 Advanced Practice Tests", "description": "Ucretsiz Cambridge C1 Advanced seviye testi — tum beceriler icin kapsamli hazirlik", "url": "https://www.cambridgeenglish.org/exams-and-tests/advanced/preparation/", "type": "practice", "level": "C1", "free": true },
    { "title": "British Council C1 Grammar — Advanced Structures", "description": "C1 seviye ileri dilbilgisi — inversion, cleft, advanced modals interaktif alistirmalar", "url": "https://learnenglish.britishcouncil.org/grammar/c1-grammar", "type": "practice", "level": "C1", "free": true },
    { "title": "BBC Learning English — Towards Advanced", "description": "C1 seviyesine gecis icin ileri dinleme, okuma ve tartisma materyalleri", "url": "https://www.bbc.co.uk/learningenglish/english/features/towards-advanced", "type": "video", "level": "C1", "free": true }
  ]
}